truecaller.py
truecaller-0.1.0.dist-info/METADATA
truecaller-0.1.0.dist-info/WHEEL
truecaller-0.1.0.dist-info/entry_points.txt
truecaller-0.1.0.dist-info/top_level.txt
truecaller-0.1.0.dist-info/RECORD
